filefix/__init__.py
filefix/core.py
filefix-0.1.3.dist-info/METADATA
filefix-0.1.3.dist-info/WHEEL
filefix-0.1.3.dist-info/entry_points.txt
filefix-0.1.3.dist-info/top_level.txt
filefix-0.1.3.dist-info/RECORD
