Metadata-Version: 2.4
Name: filefix
Version: 0.1.3
Summary: A CLI toolkit to organize files effectively.
Home-page: https://github.com/Cyrus-spc-tech/FileFixer.git
Author: cyrus
Requires-Dist: typer
Requires-Dist: pyyaml
Requires-Dist: datetime
Requires-Dist: rich
Dynamic: author
Dynamic: description
Dynamic: description-content-type
Dynamic: home-page
Dynamic: requires-dist
Dynamic: summary
